nonebot_plugin_randomnana/__init__.py
nonebot_plugin_randomnana/resource/0.jpg
nonebot_plugin_randomnana/resource/1.gif
nonebot_plugin_randomnana/resource/10.png
nonebot_plugin_randomnana/resource/100.jpg
nonebot_plugin_randomnana/resource/101.jpg
nonebot_plugin_randomnana/resource/102.jpg
nonebot_plugin_randomnana/resource/103.jpg
nonebot_plugin_randomnana/resource/104.jpg
nonebot_plugin_randomnana/resource/105.jpg
nonebot_plugin_randomnana/resource/106.jpg
nonebot_plugin_randomnana/resource/107.jpg
nonebot_plugin_randomnana/resource/108.jpg
nonebot_plugin_randomnana/resource/109.jpg
nonebot_plugin_randomnana/resource/11.png
nonebot_plugin_randomnana/resource/110.jpg
nonebot_plugin_randomnana/resource/111.jpg
nonebot_plugin_randomnana/resource/112.jpg
nonebot_plugin_randomnana/resource/113.jpg
nonebot_plugin_randomnana/resource/114.jpg
nonebot_plugin_randomnana/resource/115.jpg
nonebot_plugin_randomnana/resource/116.jpg
nonebot_plugin_randomnana/resource/117.jpg
nonebot_plugin_randomnana/resource/118.jpg
nonebot_plugin_randomnana/resource/119.jpg
nonebot_plugin_randomnana/resource/12.png
nonebot_plugin_randomnana/resource/120.jpg
nonebot_plugin_randomnana/resource/121.jpg
nonebot_plugin_randomnana/resource/122.jpg
nonebot_plugin_randomnana/resource/123.jpg
nonebot_plugin_randomnana/resource/124.jpg
nonebot_plugin_randomnana/resource/125.jpg
nonebot_plugin_randomnana/resource/126.jpg
nonebot_plugin_randomnana/resource/127.jpg
nonebot_plugin_randomnana/resource/128.jpg
nonebot_plugin_randomnana/resource/129.jpg
nonebot_plugin_randomnana/resource/13.png
nonebot_plugin_randomnana/resource/130.jpg
nonebot_plugin_randomnana/resource/131.jpg
nonebot_plugin_randomnana/resource/132.jpg
nonebot_plugin_randomnana/resource/133.jpg
nonebot_plugin_randomnana/resource/134.jpg
nonebot_plugin_randomnana/resource/135.jpg
nonebot_plugin_randomnana/resource/136.jpg
nonebot_plugin_randomnana/resource/137.jpg
nonebot_plugin_randomnana/resource/138.jpg
nonebot_plugin_randomnana-0.1.3.dist-info/LICENSE
nonebot_plugin_randomnana-0.1.3.dist-info/METADATA
nonebot_plugin_randomnana-0.1.3.dist-info/WHEEL
nonebot_plugin_randomnana-0.1.3.dist-info/RECORD
