Metadata-Version: 2.1
Name: nonebot-plugin-randomnana
Version: 0.1.3
Summary: 一款开箱即用的随机抽取神乐七奈表情包图片的插件（适用于Onebot V11）
Home-page: https://github.com/ElainaFanBoy/nonebot_plugin_randomnana
License: MIT
Author: ElainaFanBoy
Author-email: demo0929@vip.qq.com
Requires-Python: >=3.8,<4.0
Classifier: License :: OSI Approved :: MIT License
Classifier: Programming Language :: Python :: 3
Classifier: Programming Language :: Python :: 3.8
Classifier: Programming Language :: Python :: 3.9
Classifier: Programming Language :: Python :: 3.10
Classifier: Programming Language :: Python :: 3.11
Requires-Dist: nonebot-adapter-onebot (>=2.1.1,<3.0.0)
Requires-Dist: nonebot2 (>=2.0.0rc1,<3.0.0)
Project-URL: Repository, https://github.com/ElainaFanBoy/nonebot_plugin_randomnana
